LICENCE
MANIFEST.in
README.rst
setup.cfg
setup.py
bambuvizitor.egg-info/PKG-INFO
bambuvizitor.egg-info/SOURCES.txt
bambuvizitor.egg-info/dependency_links.txt
bambuvizitor.egg-info/requires.txt
bambuvizitor.egg-info/top_level.txt
vizitor/__init__.py
vizitor/admin.py
vizitor/apps.py
vizitor/models.py
vizitor/tests.py
vizitor/urls.py
vizitor/views.py
vizitor/migrations/0001_initial.py
vizitor/migrations/0002_remove_listaorder_data_order_and_more.py
vizitor/migrations/0003_order_listaorder_order.py
vizitor/migrations/0004_order_deskrisaun.py
vizitor/migrations/0005_order_resposta.py
vizitor/migrations/__init__.py
vizitor/templates/.DS_Store
vizitor/templates/ajax_buttonorder.html
vizitor/templates/ajax_buttonorderlaiha.html
vizitor/templates/ajax_orderprodutu.html
vizitor/templates/ajax_produtu.html
vizitor/templates/ajax_submitprodutu.html
vizitor/templates/anunsiu.html
vizitor/templates/baze.html
vizitor/templates/detalluanunsiu.html
vizitor/templates/detalluinformasaun.html
vizitor/templates/detallumapa.html
vizitor/templates/detallumapa2.html
vizitor/templates/detallumapaload.html
vizitor/templates/detalluprodutu.html
vizitor/templates/detalluprodutu2.html
vizitor/templates/index.html
vizitor/templates/informasaun.html
vizitor/templates/informasaungrupu.html
vizitor/templates/konabaami.html
vizitor/templates/mapa.html
vizitor/templates/mapaareabambu.html
vizitor/templates/mapaprefabrika.html
vizitor/templates/mapaviveirus.html
vizitor/templates/order.html
vizitor/templates/produtu.html
vizitor/views/__init__.py
vizitor/views/view_vizitor.py